diffpy/__init__.py
diffpy/pdffit2/__init__.py
diffpy/pdffit2/ipy_ext.py
diffpy/pdffit2/libcblas.dll
diffpy/pdffit2/output.py
diffpy/pdffit2/pdffit.py
diffpy/pdffit2/pdffit2.cpython-313-darwin.so
diffpy/pdffit2/pdffit2_app.py
diffpy/pdffit2/version.py
diffpy_pdffit2-1.5.2.dist-info/licenses/AUTHORS.rst
diffpy_pdffit2-1.5.2.dist-info/licenses/LICENSE.rst
diffpy_pdffit2-1.5.2.dist-info/METADATA
diffpy_pdffit2-1.5.2.dist-info/WHEEL
diffpy_pdffit2-1.5.2.dist-info/entry_points.txt
diffpy_pdffit2-1.5.2.dist-info/top_level.txt
diffpy_pdffit2-1.5.2.dist-info/RECORD
